pdd.py
pdd-1.7.dist-info/LICENSE
pdd-1.7.dist-info/METADATA
pdd-1.7.dist-info/WHEEL
pdd-1.7.dist-info/entry_points.txt
pdd-1.7.dist-info/top_level.txt
pdd-1.7.dist-info/RECORD
