Metadata-Version: 2.1
Name: pdd
Version: 1.7
Summary: Tiny date, time diff calculator with timers
Home-page: https://github.com/jarun/pdd
Author: Arun Prakash Jana
Author-email: engineerarun@gmail.com
License: GPLv3
Keywords: date time calculator timer
Platform: any
Classifier: Development Status :: 5 - Production/Stable
Classifier: Environment :: Console
Classifier: Intended Audience :: Developers
Classifier: Intended Audience :: End Users/Desktop
Classifier: License :: OSI Approved :: GNU General Public License v3 (GPLv3)
Classifier: Natural Language :: English
Classifier: Operating System :: OS Independent
Classifier: Programming Language :: Python :: 3
Classifier: Programming Language :: Python :: 3 :: Only
Classifier: Programming Language :: Python :: 3.7
Classifier: Programming Language :: Python :: 3.8
Classifier: Programming Language :: Python :: 3.9
Classifier: Programming Language :: Python :: 3.10
Classifier: Topic :: Utilities
Requires-Python: >=3.7
License-File: LICENSE
Requires-Dist: python-dateutil
Provides-Extra: packaging
Requires-Dist: twine ; extra == 'packaging'
Provides-Extra: tests
Requires-Dist: pytest ; extra == 'tests'
